{
    "status":0,
    "message":[
        {
            "id":1,
            "img":"https://ss0.bdstatic.com/70cFuHSh_Q1YnxGkpoWK1HF6hhy/it/u=1242273181,3992362129&fm=26&gp=0.jpg"
        },
        {
            "id":2,
            "img":"https://ss1.bdstatic.com/70cFvXSh_Q1YnxGkpoWK1HF6hhy/it/u=1802367038,1568724653&fm=26&gp=0.jpg"
        },
        {
            "id":3,
            "img":"https://ss0.bdstatic.com/70cFuHSh_Q1YnxGkpoWK1HF6hhy/it/u=1851044198,3060143424&fm=26&gp=0.jpg"
        },
        {
            "id":4,
            "img":"https://ss1.bdstatic.com/70cFuXSh_Q1YnxGkpoWK1HF6hhy/it/u=316713664,3866763343&fm=26&gp=0.jpg"
        },
        {
            "id":5,
            "img":"https://ss0.bdstatic.com/70cFuHSh_Q1YnxGkpoWK1HF6hhy/it/u=1242273181,3992362129&fm=26&gp=0.jpg"
        },
        {
            "id":6,
            "img":"https://ss0.bdstatic.com/70cFvHSh_Q1YnxGkpoWK1HF6hhy/it/u=502512318,2881168896&fm=26&gp=0.jpg"
        },{
            "id":7,
            "img":"http://img2.imgtn.bdimg.com/it/u=2955138101,2228677981&fm=26&gp=0.jpg"
        }
    ]
}